README.md
setup.cfg
setup.py
gces/__init__.py
gces/message.py
gces/pub_events.py
gces/publisher.py
gces/serializer.py
gces/sub_events.py
gces/subscriber.py
gces/tools.py
gces.egg-info/PKG-INFO
gces.egg-info/SOURCES.txt
gces.egg-info/dependency_links.txt
gces.egg-info/requires.txt
gces.egg-info/top_level.txt
gces/ext/__init__.py
gces/ext/celery/__init__.py
gces/ext/celery/publisher.py
gces/ext/pyramid/__init__.py