Metadata-Version: 2.1
Name: gces
Version: 0.0.8a0
Summary: Google Cloud Event System.
Home-page: https://github.com/debonzi/gc-event-system
Author: Daniel Debonzi
Author-email: debonzi@gmail.com
License: UNKNOWN
Platform: UNKNOWN
Classifier: Development Status :: 3 - Alpha
Classifier: Intended Audience :: Developers
Classifier: Topic :: Software Development :: Libraries :: Python Modules
Classifier: Programming Language :: Python :: 2.7
Classifier: Programming Language :: Python :: 3.5
Classifier: Programming Language :: Python :: 3.6
Provides-Extra: ci
Provides-Extra: test
Provides-Extra: celery
